{
    "name": "Hattrem",
    "national_id": 857,
    "types": [
        "Psychic"
    ],
    "abilities": [
        {
            "name": "Healer"
        },
        {
            "name": "Anticipation"
        },
        {
            "name": "Magic Bounce",
            "hidden": true
        }
    ],
    "catch_rate": 120,
    "gender_ratios": {
        "male": 0,
        "female": 100
    },
    "egg_groups": [
        "Fairy"
    ],
    "hatch_time": [
        5140,
        5396
    ],
    "height_us": "2'00\"",
    "height_eu": "0.6 m",
    "weight_us": "10.6 lbs.",
    "weight_eu": "4.8 kg",
    "base_exp_yield": 130,
    "leveling_rate": "Slow",
    "base_friendship": 50,
    "ev_yield": {
        "hp": 0,
        "atk": 0,
        "def": 0,
        "sp_atk": 2,
        "sp_def": 0,
        "speed": 0
    },
    "base_stats": {
        "hp": 57,
        "atk": 40,
        "def": 65,
        "sp_atk": 86,
        "sp_def": 73,
        "speed": 49
    },
    "evolution_from": "Hatenna",
    "evolutions": [
        {
            "to": "Hatterene",
            "level": 42
        }
    ],
    "species": "Serene Pokémon",
    "mega_evolves": false,
    "pokedex_entry": "Using the braids on its head, it pummels foes to get them to quiet down. One blow from those braids would knock out a professional boxer.",
    "move_learnset": [
        {
            "move": "Brutal Swing",
            "evo": true
        },
        {
            "move": "Brutal Swing",
            "level": 1
        },
        {
            "move": "Confusion",
            "level": 1
        },
        {
            "move": "Play Nice",
            "level": 1
        },
        {
            "move": "Life Dew",
            "level": 1
        },
        {
            "move": "Disarming Voice",
            "level": 1
        },
        {
            "move": "Aromatherapy",
            "level": 15
        },
        {
            "move": "Psybeam",
            "level": 20
        },
        {
            "move": "Heal Pulse",
            "level": 25
        },
        {
            "move": "Dazzling Gleam",
            "level": 30
        },
        {
            "move": "Calm Mind",
            "level": 37
        },
        {
            "move": "Psychic",
            "level": 44
        },
        {
            "move": "Healing Wish",
            "level": 51
        },
        {
            "move": "Magical Leaf",
            "tm": true
        },
        {
            "move": "Thunder Wave",
            "tm": true
        },
        {
            "move": "Light Screen",
            "tm": true
        },
        {
            "move": "Safeguard",
            "tm": true
        },
        {
            "move": "Rest",
            "tm": true
        },
        {
            "move": "Snore",
            "tm": true
        },
        {
            "move": "Protect",
            "tm": true
        },
        {
            "move": "Giga Drain",
            "tm": true
        },
        {
            "move": "Charm",
            "tm": true
        },
        {
            "move": "Attract",
            "tm": true
        },
        {
            "move": "Facade",
            "tm": true
        },
        {
            "move": "Helping Hand",
            "tm": true
        },
        {
            "move": "Imprison",
            "tm": true
        },
        {
            "move": "Round",
            "tm": true
        },
        {
            "move": "Draining Kiss",
            "tm": true
        },
        {
            "move": "Mystical Fire",
            "tm": true
        },
        {
            "move": "Brutal Swing",
            "tm": true
        },
        {
            "move": "Psychic",
            "tm": true
        },
        {
            "move": "Substitute",
            "tm": true
        },
        {
            "move": "Psyshock",
            "tm": true
        },
        {
            "move": "Endure",
            "tm": true
        },
        {
            "move": "Sleep Talk",
            "tm": true
        },
        {
            "move": "Baton Pass",
            "tm": true
        },
        {
            "move": "Skill Swap",
            "tm": true
        },
        {
            "move": "Calm Mind",
            "tm": true
        },
        {
            "move": "Dark Pulse",
            "tm": true
        },
        {
            "move": "Stored Power",
            "tm": true
        },
        {
            "move": "Play Rough",
            "tm": true
        },
        {
            "move": "Dazzling Gleam",
            "tm": true
        },
        {
            "move": "Aromatic Mist",
            "egg_move": true
        },
        {
            "move": "Nuzzle",
            "egg_move": true
        },
        {
            "move": "After You",
            "egg_move": true
        },
        {
            "move": "Quash",
            "egg_move": true
        }
    ]
}