{
    "name": "Silcoon",
    "national_id": 266,
    "types": [
        "Bug"
    ],
    "abilities": [
        {
            "name": "Shed Skin"
        }
    ],
    "catch_rate": 120,
    "gender_ratios": {
        "male": 50,
        "female": 50
    },
    "egg_groups": [
        "Bug"
    ],
    "hatch_time": [
        4080,
        4334
    ],
    "height_us": "2'00\"",
    "height_eu": "0.6 m",
    "weight_us": "22.0 lbs.",
    "weight_eu": "10.0 kg",
    "base_exp_yield": 72,
    "leveling_rate": "Medium Fast",
    "base_friendship": 70,
    "ev_yield": {
        "hp": 0,
        "atk": 0,
        "def": 2,
        "sp_atk": 0,
        "sp_def": 0,
        "speed": 0
    },
    "base_stats": {
        "hp": 50,
        "atk": 35,
        "def": 55,
        "sp_atk": 25,
        "sp_def": 25,
        "speed": 15
    },
    "evolution_from": "Wurmple",
    "evolutions": [
        {
            "to": "Beautifly",
            "level": 10
        }
    ],
    "species": "Cocoon Pokémon",
    "mega_evolves": false,
    "pokedex_entry": "Silcoon was thought to endure hunger and not consume anything before its evolution. However, it is now thought that this Pokémon slakes its thirst by drinking rainwater that collects on its silk.",
    "move_learnset": [
        {
            "move": "Harden",
            "level": 1
        }
    ]
}