{
    "index_number": 614,
    "name": "Thousand Arrows",
    "type": "Ground",
    "pp": 10,
    "max_pp": 16,
    "power": 90,
    "accuracy": 100,
    "category": "physical",
    "priority": 0,
    "critical_hit": 0,
    "target": "target_adjacent_single",
    "makes_contact": false,
    "affected_by_protect": true,
    "affected_by_magic_coat": false,
    "affected_by_snatch": false,
    "affected_by_mirror_move": false,
    "affected_by_kings_rock": true,
    "description": "This move also hits opposing Pokémon that are in the air. Those Pokémon are knocked down to the ground."
}