{
    "walking": [
        {
            "name": "Raticate",
            "min_level": 30,
            "max_level": 35,
            "rarity": [
                0,
                30
            ],
            "sos": [
                {
                    "name": "Raticate",
                    "chance": 100
                }
            ],
            "types": [
                "Dark",
                "Normal"
            ]
        },
        {
            "name": "Slowpoke",
            "min_level": 30,
            "max_level": 35,
            "rarity": [
                20,
                20
            ],
            "sos": [
                {
                    "name": "Slowpoke",
                    "chance": 100
                }
            ],
            "types": [
                "Water",
                "Psychic"
            ]
        },
        {
            "name": "Pelipper",
            "min_level": 30,
            "max_level": 35,
            "rarity": [
                50,
                50
            ],
            "sos": [
                {
                    "name": "Pelipper",
                    "chance": 100
                }
            ],
            "types": [
                "Water",
                "Flying"
            ]
        },
        {
            "name": "Gumshoos",
            "min_level": 30,
            "max_level": 35,
            "rarity": [
                30,
                0
            ],
            "sos": [
                {
                    "name": "Gumshoos",
                    "chance": 100
                }
            ],
            "types": [
                "Normal"
            ]
        },
        {
            "name": "Scraggy",
            "min_level": 32,
            "max_level": 35,
            "rarity": [
                30,
                30
            ],
            "sos": [
                {
                    "name": "Scraggy",
                    "chance": 100
                }
            ],
            "types": [
                "Dark",
                "Fighting"
            ]
        },
        {
            "name": "Crabrawler",
            "min_level": 30,
            "max_level": 35,
            "rarity": [
                10,
                10
            ],
            "sos": [
                {
                    "name": "Crabrawler",
                    "chance": 100
                }
            ],
            "pile": true,
            "types": [
                "Fighting"
            ]
        }
    ]
}