{
    "walking": [
        {
            "name": "Raticate",
            "min_level": 28,
            "max_level": 33,
            "rarity": [
                0,
                30
            ],
            "sos": [
                {
                    "name": "Castform",
                    "chance": 1,
                    "weather": "hail"
                },
                {
                    "name": "Castform",
                    "chance": 11,
                    "weather": "rain"
                },
                {
                    "name": "Castform",
                    "chance": 11,
                    "weather": "sandstorm"
                },
                {
                    "name": "Vanillite",
                    "chance": 10,
                    "weather": "hail"
                },
                {
                    "name": "Raticate",
                    "chance": 100
                }
            ],
            "types": [
                "Dark",
                "Normal"
            ]
        },
        {
            "name": "Sandshrew",
            "min_level": 28,
            "max_level": 33,
            "rarity": [
                10,
                10
            ],
            "sos": [
                {
                    "name": "Castform",
                    "chance": 1,
                    "weather": "hail"
                },
                {
                    "name": "Castform",
                    "chance": 11,
                    "weather": "rain"
                },
                {
                    "name": "Castform",
                    "chance": 11,
                    "weather": "sandstorm"
                },
                {
                    "name": "Vanillite",
                    "chance": 10,
                    "weather": "hail"
                },
                {
                    "name": "Sandshrew",
                    "chance": 100
                }
            ],
            "types": [
                "Ice",
                "Steel"
            ]
        },
        {
            "name": "Vulpix",
            "min_level": 28,
            "max_level": 33,
            "rarity": [
                10,
                10
            ],
            "sos": [
                {
                    "name": "Castform",
                    "chance": 1,
                    "weather": "hail"
                },
                {
                    "name": "Castform",
                    "chance": 11,
                    "weather": "rain"
                },
                {
                    "name": "Castform",
                    "chance": 11,
                    "weather": "sandstorm"
                },
                {
                    "name": "Vanillite",
                    "chance": 10,
                    "weather": "hail"
                },
                {
                    "name": "Vulpix",
                    "chance": 100
                }
            ],
            "types": [
                "Ice"
            ]
        },
        {
            "name": "Pelipper",
            "min_level": 28,
            "max_level": 33,
            "rarity": [
                30,
                30
            ],
            "sos": [
                {
                    "name": "Castform",
                    "chance": 1,
                    "weather": "hail"
                },
                {
                    "name": "Castform",
                    "chance": 11,
                    "weather": "rain"
                },
                {
                    "name": "Castform",
                    "chance": 11,
                    "weather": "sandstorm"
                },
                {
                    "name": "Vanillite",
                    "chance": 10,
                    "weather": "hail"
                },
                {
                    "name": "Pelipper",
                    "chance": 100
                }
            ],
            "types": [
                "Water",
                "Flying"
            ]
        },
        {
            "name": "Absol",
            "min_level": 28,
            "max_level": 33,
            "rarity": [
                10,
                10
            ],
            "sos": [
                {
                    "name": "Castform",
                    "chance": 1,
                    "weather": "hail"
                },
                {
                    "name": "Castform",
                    "chance": 11,
                    "weather": "rain"
                },
                {
                    "name": "Castform",
                    "chance": 11,
                    "weather": "sandstorm"
                },
                {
                    "name": "Vanillite",
                    "chance": 10,
                    "weather": "hail"
                },
                {
                    "name": "Absol",
                    "chance": 100
                }
            ],
            "types": [
                "Dark"
            ]
        },
        {
            "name": "Snorunt",
            "min_level": 28,
            "max_level": 33,
            "rarity": [
                20,
                20
            ],
            "sos": [
                {
                    "name": "Castform",
                    "chance": 1,
                    "weather": "hail"
                },
                {
                    "name": "Castform",
                    "chance": 11,
                    "weather": "rain"
                },
                {
                    "name": "Castform",
                    "chance": 11,
                    "weather": "sandstorm"
                },
                {
                    "name": "Vanillite",
                    "chance": 10,
                    "weather": "hail"
                },
                {
                    "name": "Snorunt",
                    "chance": 100
                }
            ],
            "types": [
                "Ice"
            ]
        },
        {
            "name": "Gumshoos",
            "min_level": 28,
            "max_level": 33,
            "rarity": [
                30,
                0
            ],
            "sos": [
                {
                    "name": "Castform",
                    "chance": 1,
                    "weather": "hail"
                },
                {
                    "name": "Castform",
                    "chance": 11,
                    "weather": "rain"
                },
                {
                    "name": "Castform",
                    "chance": 11,
                    "weather": "sandstorm"
                },
                {
                    "name": "Vanillite",
                    "chance": 10,
                    "weather": "hail"
                },
                {
                    "name": "Gumshoos",
                    "chance": 100
                }
            ],
            "types": [
                "Normal"
            ]
        }
    ]
}