{
    "pokemon": [
        {
            "name": "Kecleon",
            "field": "Walking",
            "min_level": 17,
            "max_level": 20,
            "rarity": [
                50,
                50
            ],
            "sos": [
                {
                    "name": "Kecleon",
                    "chance": 100
                }
            ]
        },
        {
            "name": "Wimpod",
            "field": "Walking",
            "min_level": 17,
            "max_level": 20,
            "rarity": [
                50,
                50
            ]
        }
    ]
}