{
    "pokemon": [
        {
            "name": "Zubat",
            "field": "Walking",
            "min_level": 10,
            "max_level": 14,
            "rarity": [
                30,
                30
            ],
            "sos": [
                {
                    "name": "Zubat",
                    "chance": 100
                }
            ]
        },
        {
            "name": "Psyduck",
            "field": "Walking",
            "min_level": 11,
            "max_level": 14,
            "rarity": [
                10,
                10
            ],
            "sos": [
                {
                    "name": "Psyduck",
                    "chance": 100
                }
            ]
        },
        {
            "name": "Mawile",
            "field": "Walking",
            "min_level": 11,
            "max_level": 14,
            "rarity": [
                30,
                30
            ],
            "sos": [
                {
                    "name": "Mawile",
                    "chance": 100
                }
            ]
        },
        {
            "name": "Diglett",
            "field": "Walking",
            "min_level": 10,
            "max_level": 13,
            "rarity": [
                20,
                20
            ],
            "sos": [
                {
                    "name": "Diglett",
                    "chance": 100
                }
            ]
        },
        {
            "name": "Roggenrola",
            "field": "Walking",
            "min_level": 10,
            "max_level": 14,
            "rarity": [
                30,
                30
            ],
            "sos": [
                {
                    "name": "Roggenrola",
                    "chance": 100
                }
            ]
        },
        {
            "name": "Carbink",
            "field": "Walking",
            "min_level": 10,
            "max_level": 14,
            "rarity": [
                20,
                20
            ],
            "sos": [
                {
                    "name": "Carbink",
                    "chance": 50
                },
                {
                    "name": "Sableye",
                    "chance": 50
                }
            ]
        },
        {
            "name": "Machop",
            "field": "Walking",
            "min_level": 10,
            "max_level": 14,
            "rarity": [
                30,
                30
            ],
            "sos": [
                {
                    "name": "Machop",
                    "chance": 100
                }
            ]
        },
        {
            "name": "Spinda",
            "field": "Walking",
            "min_level": 10,
            "max_level": 14,
            "rarity": [
                10,
                10
            ],
            "sos": [
                {
                    "name": "Spinda",
                    "chance": 100
                }
            ]
        },
        {
            "name": "Rockruff",
            "field": "Walking",
            "min_level": 10,
            "max_level": 14,
            "rarity": [
                20,
                20
            ],
            "sos": [
                {
                    "name": "Rockruff",
                    "chance": 100
                }
            ]
        },
        {
            "name": "Zubat",
            "field": "Surfing",
            "min_level": 15,
            "max_level": 18,
            "rarity": [
                95,
                95
            ],
            "sos": [
                {
                    "name": "Zubat",
                    "chance": 100
                }
            ]
        },
        {
            "name": "Psyduck",
            "field": "Surfing",
            "min_level": 15,
            "max_level": 18,
            "rarity": [
                20,
                20
            ],
            "sos": [
                {
                    "name": "Psyduck",
                    "chance": 100
                }
            ]
        }
    ]
}