{
    "walking": [
        {
            "name": "Zubat",
            "min_level": 13,
            "max_level": 15,
            "rarity": [
                30
            ],
            "types": [
                "Poison",
                "Flying"
            ]
        },
        {
            "name": "Whismur",
            "min_level": 13,
            "max_level": 15,
            "rarity": [
                30
            ],
            "types": [
                "Normal"
            ]
        },
        {
            "name": "Meditite",
            "min_level": 13,
            "max_level": 15,
            "rarity": [
                30
            ],
            "types": [
                "Fighting",
                "Psychic"
            ]
        },
        {
            "name": "Axew",
            "min_level": 13,
            "max_level": 15,
            "rarity": [
                10
            ],
            "types": [
                "Dragon"
            ]
        }
    ]
}